{
  "scriptVersion": "14",
  "dpi": 160,
  "sourcePdfSha256": "cfafbd1fee916f1e541883343793b4819d7098d2435129d257388a1664021b8b",
  "crops": {
    "1": {
      "sourcePage": 8,
      "box": [
        28.0,
        50.85,
        584.0,
        263.7
      ]
    },
    "2": {
      "sourcePage": 8,
      "box": [
        28.0,
        263.7,
        584.0,
        702.372
      ]
    },
    "3": {
      "sourcePage": 9,
      "box": [
        28.0,
        50.4,
        584.0,
        698.6
      ]
    },
    "10": {
      "sourcePage": 10,
      "box": [
        28.0,
        50.85,
        584.0,
        339.3
      ]
    },
    "11": {
      "sourcePage": 10,
      "box": [
        28.0,
        339.3,
        584.0,
        702.372
      ]
    },
    "13": {
      "sourcePage": 11,
      "box": [
        28.0,
        306.9,
        584.0,
        495.9
      ]
    },
    "14": {
      "sourcePage": 11,
      "box": [
        28.0,
        495.9,
        584.0,
        702.372
      ]
    },
    "17": {
      "sourcePage": 12,
      "box": [
        28.0,
        50.85,
        584.0,
        486.9
      ]
    },
    "18": {
      "sourcePage": 12,
      "box": [
        28.0,
        486.9,
        584.0,
        702.372
      ]
    },
    "24": {
      "sourcePage": 13,
      "box": [
        28.0,
        50.85,
        584.0,
        255.6
      ]
    },
    "25": {
      "sourcePage": 13,
      "box": [
        28.0,
        255.6,
        584.0,
        702.372
      ]
    },
    "28": {
      "sourcePage": 14,
      "box": [
        28.0,
        50.85,
        584.0,
        267.3
      ]
    },
    "29": {
      "sourcePage": 14,
      "box": [
        28.0,
        267.3,
        584.0,
        498.15
      ]
    },
    "30": {
      "sourcePage": 14,
      "box": [
        28.0,
        498.15,
        584.0,
        702.372
      ]
    },
    "31": {
      "sourcePage": 20,
      "box": [
        28.0,
        50.85,
        584.0,
        279.45
      ]
    },
    "32": {
      "sourcePage": 20,
      "box": [
        28.0,
        279.45,
        584.0,
        702.372
      ]
    },
    "33": {
      "sourcePage": 21,
      "box": [
        28.0,
        50.85,
        584.0,
        256.5
      ]
    },
    "34": {
      "sourcePage": 21,
      "box": [
        28.0,
        256.5,
        584.0,
        702.372
      ]
    },
    "35": {
      "sourcePage": 22,
      "box": [
        28.0,
        50.85,
        584.0,
        268.65
      ]
    },
    "36": {
      "sourcePage": 22,
      "box": [
        28.0,
        268.65,
        584.0,
        469.35
      ]
    },
    "37": {
      "sourcePage": 22,
      "box": [
        28.0,
        469.35,
        584.0,
        702.372
      ]
    },
    "38": {
      "sourcePage": 23,
      "box": [
        28.0,
        50.85,
        584.0,
        702.372
      ]
    }
  },
  "outputs": {
    "1": {
      "width": 1116,
      "height": 380
    },
    "2": {
      "width": 1083,
      "height": 729
    },
    "3": {
      "width": 1101,
      "height": 1387
    },
    "10": {
      "width": 1109,
      "height": 536
    },
    "11": {
      "width": 886,
      "height": 617
    },
    "13": {
      "width": 708,
      "height": 326
    },
    "14": {
      "width": 787,
      "height": 416
    },
    "17": {
      "width": 1015,
      "height": 852
    },
    "18": {
      "width": 849,
      "height": 389
    },
    "24": {
      "width": 1113,
      "height": 354
    },
    "25": {
      "width": 1039,
      "height": 324
    },
    "28": {
      "width": 1108,
      "height": 381
    },
    "29": {
      "width": 1069,
      "height": 416
    },
    "30": {
      "width": 1110,
      "height": 356
    },
    "31": {
      "width": 662,
      "height": 414
    },
    "32": {
      "width": 449,
      "height": 416
    },
    "33": {
      "width": 618,
      "height": 356
    },
    "34": {
      "width": 1124,
      "height": 604
    },
    "35": {
      "width": 1115,
      "height": 381
    },
    "36": {
      "width": 1047,
      "height": 350
    },
    "37": {
      "width": 1035,
      "height": 356
    },
    "38": {
      "width": 1140,
      "height": 704
    }
  }
}
